hanky/__about__.py
hanky/__init__.py
hanky/__main__.py
hanky/cli.py
hanky/config.py
hanky/fs.py
hanky/hanky.py
hanky/media.py
hanky-0.0.3.dist-info/METADATA
hanky-0.0.3.dist-info/WHEEL
hanky-0.0.3.dist-info/entry_points.txt
hanky-0.0.3.dist-info/licenses/LICENSE
hanky-0.0.3.dist-info/RECORD
