Metadata-Version: 2.3
Name: hanky
Version: 0.0.3
Summary: Simple library and command line tool for loading flash cards into anki.
Project-URL: Homepage, https://github.com/Haeata-Ash/hanky
Project-URL: Issues, https://github.com/Haeata-Ash/hanky/issues
Author-email: HBA <hanky-pypi.8ebs0@simplelogin.com>
License-File: LICENSE
Keywords: anki
Classifier: Environment :: Console
Classifier: License :: OSI Approved :: MIT License
Classifier: Operating System :: Unix
Classifier: Programming Language :: Python :: 3
Requires-Python: >=3.8
Requires-Dist: anki
Requires-Dist: psutil
Provides-Extra: tos
Requires-Dist: boto3; extra == 'tos'
